ImageFetchPy/__init__.py
ImageFetchPy/cli.py
ImageFetchPy/main.py
ImageFetchPy-1.2.dist-info/METADATA
ImageFetchPy-1.2.dist-info/WHEEL
ImageFetchPy-1.2.dist-info/entry_points.txt
ImageFetchPy-1.2.dist-info/top_level.txt
ImageFetchPy-1.2.dist-info/RECORD
