Metadata-Version: 2.1
Name: ImageFetchPy
Version: 1.2
Summary: A library for scraping and downloading images from the web.
Home-page: https://github.com/sai-3000/ImageFetchPY
Author: Sai Smaran Panda
Author-email: smaran06ncn@gmail.com
Project-URL: Source, https://github.com/sai-3000/ImageFetchPY
Project-URL: Tracker, https://github.com/sai-3000/ImageFetchPY
Classifier: Development Status :: 5 - Production/Stable
Classifier: Intended Audience :: Developers
Classifier: License :: OSI Approved :: MIT License
Classifier: Programming Language :: Python :: 3
Classifier: Programming Language :: Python :: 3.6
Classifier: Programming Language :: Python :: 3.7
Classifier: Programming Language :: Python :: 3.8
Classifier: Programming Language :: Python :: 3.9
Requires-Dist: python-magic-bin ==0.4.14
Requires-Dist: progressbar2
Requires-Dist: urllib3
Requires-Dist: requests
